mach2viz/__init__.py
mach2viz/viz.py
mach2viz/static/404 2.html
mach2viz/static/404.html
mach2viz/static/asset-manifest 2.json
mach2viz/static/asset-manifest.json
mach2viz/static/favicon 2.ico
mach2viz/static/favicon.ico
mach2viz/static/index 2.html
mach2viz/static/index.html
mach2viz/static/logo 2.png
mach2viz/static/logo.png
mach2viz/static/logo192 2.png
mach2viz/static/logo192.png
mach2viz/static/logo512 2.png
mach2viz/static/logo512.png
mach2viz/static/manifest 2.json
mach2viz/static/manifest.json
mach2viz/static/precache-manifest.bff4b3e56643d1f56fb1a0b5267631ae.js
mach2viz/static/robots 2.txt
mach2viz/static/robots.txt
mach2viz/static/service-worker 2.js
mach2viz/static/service-worker.js
mach2viz/static/static/css/main.d708e8a3.chunk 2.css
mach2viz/static/static/css/main.d708e8a3.chunk.css
mach2viz/static/static/css/main.d708e8a3.chunk.css 2.map
mach2viz/static/static/css/main.d708e8a3.chunk.css.map
mach2viz/static/static/js/1.84db0e82.chunk 2.js
mach2viz/static/static/js/1.84db0e82.chunk.js
mach2viz/static/static/js/1.84db0e82.chunk.js 2.map
mach2viz/static/static/js/1.84db0e82.chunk.js.map
mach2viz/static/static/js/2.49bf6ea5.chunk 2.js
mach2viz/static/static/js/2.49bf6ea5.chunk.js
mach2viz/static/static/js/2.49bf6ea5.chunk.js 2.map
mach2viz/static/static/js/2.49bf6ea5.chunk.js.map
mach2viz/static/static/js/main.5a8e2600.chunk.js
mach2viz/static/static/js/main.5a8e2600.chunk.js.map
mach2viz/static/static/js/runtime~main.26043361 2.js
mach2viz/static/static/js/runtime~main.26043361.js
mach2viz/static/static/js/runtime~main.26043361.js 2.map
mach2viz/static/static/js/runtime~main.26043361.js.map
mach2viz/static/static/media/cursor8.e5d12866 2.cur
mach2viz/static/static/media/cursor8.e5d12866.cur
mach2viz/static/static/media/lucon.97a55c95 2.ttf
mach2viz/static/static/media/lucon.97a55c95.ttf
mach2viz/static/static/media/sample_page.17167d94 2.png
mach2viz/static/static/media/sample_page.17167d94.png
mach2_viz-0.0.4.dist-info/METADATA
mach2_viz-0.0.4.dist-info/WHEEL
mach2_viz-0.0.4.dist-info/top_level.txt
mach2_viz-0.0.4.dist-info/RECORD
